LICENSE
MANIFEST.in
README.md
pyproject.toml
setup.cfg
setup.py
mmdet/__init__.py
mmdet/registry.py
mmdet/version.py
mmdet/.mim/dataset-index.yml
mmdet/.mim/model-index.yml
mmdet/.mim/configs/_base_/default_runtime.py
mmdet/.mim/configs/_base_/datasets/ade20k_instance.py
mmdet/.mim/configs/_base_/datasets/ade20k_panoptic.py
mmdet/.mim/configs/_base_/datasets/ade20k_semantic.py
mmdet/.mim/configs/_base_/datasets/cityscapes_detection.py
mmdet/.mim/configs/_base_/datasets/cityscapes_instance.py
mmdet/.mim/configs/_base_/datasets/coco_caption.py
mmdet/.mim/configs/_base_/datasets/coco_detection.py
mmdet/.mim/configs/_base_/datasets/coco_instance.py
mmdet/.mim/configs/_base_/datasets/coco_instance_semantic.py
mmdet/.mim/configs/_base_/datasets/coco_panoptic.py
mmdet/.mim/configs/_base_/datasets/coco_semantic.py
mmdet/.mim/configs/_base_/datasets/deepfashion.py
mmdet/.mim/configs/_base_/datasets/dsdl.py
mmdet/.mim/configs/_base_/datasets/isaid_instance.py
mmdet/.mim/configs/_base_/datasets/lvis_v0.5_instance.py
mmdet/.mim/configs/_base_/datasets/lvis_v1_instance.py
mmdet/.mim/configs/_base_/datasets/mot_challenge.py
mmdet/.mim/configs/_base_/datasets/mot_challenge_det.py
mmdet/.mim/configs/_base_/datasets/mot_challenge_reid.py
mmdet/.mim/configs/_base_/datasets/objects365v1_detection.py
mmdet/.mim/configs/_base_/datasets/objects365v2_detection.py
mmdet/.mim/configs/_base_/datasets/openimages_detection.py
mmdet/.mim/configs/_base_/datasets/refcoco+.py
mmdet/.mim/configs/_base_/datasets/refcoco.py
mmdet/.mim/configs/_base_/datasets/refcocog.py
mmdet/.mim/configs/_base_/datasets/semi_coco_detection.py
mmdet/.mim/configs/_base_/datasets/v3det.py
mmdet/.mim/configs/_base_/datasets/voc0712.py
mmdet/.mim/configs/_base_/datasets/wider_face.py
mmdet/.mim/configs/_base_/datasets/youtube_vis.py
mmdet/.mim/configs/_base_/models/cascade-mask-rcnn_r50_fpn.py
mmdet/.mim/configs/_base_/models/cascade-rcnn_r50_fpn.py
mmdet/.mim/configs/_base_/models/fast-rcnn_r50_fpn.py
onedl_mmdetection.egg-info/PKG-INFO
onedl_mmdetection.egg-info/SOURCES.txt
onedl_mmdetection.egg-info/dependency_links.txt
onedl_mmdetection.egg-info/requires.txt
onedl_mmdetection.egg-info/top_level.txt