Metadata-Version: 2.4
Name: onedl-mmdetection
Version: 3.4.0
Summary: OneDL Detection Toolbox and Benchmark
Author-email: OneDL MMDetection Contributors <oss-team@vbti.nl>
License-Expression: Apache-2.0
Project-URL: Homepage, https://github.com/VBTI-development/onedl-mmdetection
Project-URL: Repository, https://github.com/VBTI-development/onedl-mmdetection
Project-URL: Documentation, https://onedl-mmdetection.readthedocs.io/en/latest/
Keywords: computer vision,object detection,instance segmentation
Classifier: Development Status :: 5 - Production/Stable
Classifier: Operating System :: OS Independent
Classifier: Programming Language :: Python :: 3
Classifier: Programming Language :: Python :: 3.10
Classifier: Programming Language :: Python :: 3.11
Classifier: Topic :: Scientific/Engineering :: Artificial Intelligence
Requires-Python: >=3.10
License-File: LICENSE
Requires-Dist: imgaug
Requires-Dist: matplotlib
Requires-Dist: numpy
Requires-Dist: pycocotools
Requires-Dist: scipy
Requires-Dist: shapely
Requires-Dist: six
Requires-Dist: terminaltables
Requires-Dist: tqdm
Provides-Extra: albu
Requires-Dist: albumentations~=1.4; extra == "albu"
Provides-Extra: multimodal
Requires-Dist: fairscale; extra == "multimodal"
Requires-Dist: jsonlines; extra == "multimodal"
Requires-Dist: nltk; extra == "multimodal"
Requires-Dist: pycocoevalcap; extra == "multimodal"
Requires-Dist: transformers==4.53.3; extra == "multimodal"
Provides-Extra: mminstall
Requires-Dist: onedl-mmcv>=2.0.0; extra == "mminstall"
Requires-Dist: onedl-mmengine<1.0.0,>=0.8.3; extra == "mminstall"
Provides-Extra: optional
Requires-Dist: cityscapesscripts; extra == "optional"
Requires-Dist: emoji; extra == "optional"
Requires-Dist: fairscale; extra == "optional"
Requires-Dist: faster-coco-eval; extra == "optional"
Requires-Dist: imagecorruptions; extra == "optional"
Requires-Dist: scikit-learn; extra == "optional"
Provides-Extra: torch
Requires-Dist: torch; extra == "torch"
Requires-Dist: torchvision; extra == "torch"
Provides-Extra: tracking
Requires-Dist: onedl-mmpretrain; extra == "tracking"
Requires-Dist: motmetrics; extra == "tracking"
Requires-Dist: numpy; extra == "tracking"
Requires-Dist: scikit-learn; extra == "tracking"
Requires-Dist: seaborn; extra == "tracking"
Requires-Dist: lap; extra == "tracking"
Dynamic: license-file
